EpigeneticPacemaker/EPMBase.py
EpigeneticPacemaker/EPMCompute.py
EpigeneticPacemaker/EpigeneticPacemaker.py
EpigeneticPacemaker/EpigeneticPacemakerCV.py
EpigeneticPacemaker/__init__.py
EpigeneticPacemaker/ExampleData/DataSets.py
EpigeneticPacemaker/ExampleData/GSE74193_test.tsv.gz
EpigeneticPacemaker/ExampleData/GSE74193_train.tsv.gz
EpigeneticPacemaker/ExampleData/__init__.py
EpigeneticPacemaker-0.0.3.dist-info/METADATA
EpigeneticPacemaker-0.0.3.dist-info/WHEEL
EpigeneticPacemaker-0.0.3.dist-info/top_level.txt
EpigeneticPacemaker-0.0.3.dist-info/RECORD
