Metadata-Version: 2.1
Name: EpigeneticPacemaker
Version: 0.0.3
Summary: Epigenetic State Modeling Utility
Home-page: https://github.com/NuttyLogic/EpigeneticPacemaker
Author: Colin P. Farrell, Sagi Snir
Author-email: colinpfarrell@gmail.com
License: MIT
Project-URL: Documentation, https://epigeneticpacemaker.readthedocs.io
Platform: UNKNOWN
Requires: scipy
Requires: numpy
Requires: tqdm
Requires-Python: >=3.6
Requires-Dist: numpy (>=1.16.3)
Requires-Dist: tqdm (>=4.31.1)
Requires-Dist: scipy (>=1.3.0)
